gitea_client/__init__.py
gitea_client/auth.py
gitea_client/entities.py
gitea_client/interface.py
gitea_client/updates.py
gitea_client/_implementation/__init__.py
gitea_client/_implementation/http_utils.py
tests/__init__.py
tests/http_utils_test.py
tests/interface_test.py
tests/gogs_client/__init__.py
tests/gogs_client/auth.py
tests/gogs_client/entities.py
tests/gogs_client/interface.py
tests/gogs_client/updates.py
tests/gogs_client/_implementation/__init__.py
tests/gogs_client/_implementation/http_utils.py
gitea_client-1.0.9.dist-info/LICENSE.txt
gitea_client-1.0.9.dist-info/METADATA
gitea_client-1.0.9.dist-info/WHEEL
gitea_client-1.0.9.dist-info/top_level.txt
gitea_client-1.0.9.dist-info/RECORD
