Metadata-Version: 2.1
Name: gitea-client
Version: 1.0.9
Summary: A python library for interacting with a Gitea server
Home-page: https://github.com/unfoldingWord-dev/python-gitea-client
Author: unfoldingWord
Author-email: dev@unfoldingword.org
License: MIT
Keywords: gitea,gogs,http,client
Platform: UNKNOWN
Classifier: License :: OSI Approved :: MIT License
Classifier: Programming Language :: Python :: 2.7
Classifier: Programming Language :: Python :: 3
Classifier: Programming Language :: Python :: 3.3
Classifier: Programming Language :: Python :: 3.4
Classifier: Programming Language :: Python :: 3.5
Requires-Dist: future
Requires-Dist: requests
Requires-Dist: attrs
